typecode/__init__.py
typecode/apache-2.0.LICENSE
typecode/bsd-new.LICENSE
typecode/bsd-simplified.LICENSE
typecode/contenttype.py
typecode/entropy.py
typecode/extractible.py
typecode/magic2.py
typecode/magic2.py.ABOUT
typecode/mimetypes.py
typecode/mimetypes.py.ABOUT
typecode/mit.LICENSE
typecode/public-domain.LICENSE
typecode/pygments_lexers.py
typecode/pygments_lexers.py.ABOUT
typecode/pygments_lexers.py.NOTICE
typecode/pygments_lexers_mapping.py
typecode/pygments_lexers_mapping.py.ABOUT
typecode/pygments_lexers_mapping.py.NOTICE
typecode/python.LICENSE
typecode/_vendor/__init__.py
typecode/_vendor/apache-2.0.LICENSE
typecode/_vendor/bsd-new.LICENSE
typecode/_vendor/pygments.ABOUT
typecode/_vendor/pygments.NOTICE
typecode/_vendor/pygments/LICENSE
typecode/_vendor/pygments/__init__.py
typecode/_vendor/pygments/__main__.py
typecode/_vendor/pygments/cmdline.py
typecode/_vendor/pygments/console.py
typecode/_vendor/pygments/filter.py
typecode/_vendor/pygments/formatter.py
typecode/_vendor/pygments/lexer.py
typecode/_vendor/pygments/modeline.py
typecode/_vendor/pygments/plugin.py
typecode/_vendor/pygments/regexopt.py
typecode/_vendor/pygments/scanner.py
typecode/_vendor/pygments/sphinxext.py
typecode/_vendor/pygments/style.py
typecode/_vendor/pygments/token.py
typecode/_vendor/pygments/unistring.py
typecode/_vendor/pygments/util.py
typecode/_vendor/pygments/filters/__init__.py
typecode/_vendor/pygments/formatters/__init__.py
typecode/_vendor/pygments/formatters/_mapping.py
typecode/_vendor/pygments/formatters/bbcode.py
typecode/_vendor/pygments/formatters/html.py
typecode/_vendor/pygments/formatters/img.py
typecode/_vendor/pygments/formatters/irc.py
typecode/_vendor/pygments/formatters/latex.py
typecode/_vendor/pygments/formatters/other.py
typecode/_vendor/pygments/formatters/rtf.py
typecode/_vendor/pygments/formatters/svg.py
typecode/_vendor/pygments/formatters/terminal.py
typecode/_vendor/pygments/formatters/terminal256.py
typecode/_vendor/pygments/lexers/__init__.py
typecode-30.0.2.dist-info/AUTHORS.rst
typecode-30.0.2.dist-info/CHANGELOG.rst
typecode-30.0.2.dist-info/CODE_OF_CONDUCT.rst
typecode-30.0.2.dist-info/METADATA
typecode-30.0.2.dist-info/NOTICE
typecode-30.0.2.dist-info/WHEEL
typecode-30.0.2.dist-info/apache-2.0.LICENSE
typecode-30.0.2.dist-info/top_level.txt
typecode-30.0.2.dist-info/RECORD
